<?xml version="1.0" encoding="utf-8"?>
<page>
	<items>
								<item>
					<name>骑自行车，山地自行车，BMX</name>
					<calorie1>502</calorie1>
					<calorie2>598</calorie2>
					<calorie3>695</calorie3>
					<calorie4>791</calorie4>
					<id>1</id>
				</item>
				<item>
					<name>骑自行车，不到16kmh，休闲骑自行车</name>
					<calorie1>236</calorie1>
					<calorie2>281</calorie2>
					<calorie3>327</calorie3>
					<calorie4>372</calorie4>
					<id>2</id>
				</item>
				<item>
					<name>骑自行车，超过32kmh，赛车</name>
					<calorie1>944</calorie1>
					<calorie2>1126</calorie2>
					<calorie3>1308</calorie3>
					<calorie4>1489</calorie4>
					<id>3</id>
				</item>
				<item>
					<name>骑自行车，16-19kmh，光</name>
					<calorie1>354</calorie1>
					<calorie2>422</calorie2>
					<calorie3>490</calorie3>
					<calorie4>558</calorie4>
					<id>4</id>
				</item>
				<item>
					<name>骑自行车，20-22kmh，中度</name>
					<calorie1>472</calorie1>
					<calorie2>563</calorie2>
					<calorie3>654</calorie3>
					<calorie4>745</calorie4>
					<id>5</id>
				</item>
				<item>
					<name>骑自行车，23-25​​kmh，苍劲</name>
					<calorie1>590</calorie1>
					<calorie2>704</calorie2>
					<calorie3>817</calorie3>
					<calorie4>931</calorie4>
					<id>6</id>
				</item>
				<item>
					<name>骑自行车，26-30kmh，速度非常快，赛车</name>
					<calorie1>708</calorie1>
					<calorie2>844</calorie2>
					<calorie3>981</calorie3>
					<calorie4>1117</calorie4>
					<id>7</id>
				</item>
				<item>
					<name>骑独轮车</name>
					<calorie1>295</calorie1>
					<calorie2>352</calorie2>
					<calorie3>409</calorie3>
					<calorie4>465</calorie4>
					<id>8</id>
				</item>
				<item>
					<name>骑运动自行车，很轻</name>
					<calorie1>177</calorie1>
					<calorie2>211</calorie2>
					<calorie3>245</calorie3>
					<calorie4>279</calorie4>
					<id>9</id>
				</item>
				<item>
					<name>骑运动自行车，轻</name>
					<calorie1>325</calorie1>
					<calorie2>387</calorie2>
					<calorie3>449</calorie3>
					<calorie4>512</calorie4>
					<id>10</id>
				</item>
				<item>
					<name>骑运动自行车，中度</name>
					<calorie1>413</calorie1>
					<calorie2>493</calorie2>
					<calorie3>572</calorie3>
					<calorie4>651</calorie4>
					<id>11</id>
				</item>
				<item>
					<name>骑运动自行车，苍劲</name>
					<calorie1>620</calorie1>
					<calorie2>739</calorie2>
					<calorie3>858</calorie3>
					<calorie4>977</calorie4>
					<id>12</id>
				</item>
				<item>
					<name>骑运动自行车，很生猛</name>
					<calorie1>738</calorie1>
					<calorie2>880</calorie2>
					<calorie3>1022</calorie3>
					<calorie4>1163</calorie4>
					<id>13</id>
				</item>
				<item>
					<name>健美操，蓬勃向上，俯卧撑，仰卧起坐</name>
					<calorie1>472</calorie1>
					<calorie2>563</calorie2>
					<calorie3>654</calorie3>
					<calorie4>745</calorie4>
					<id>14</id>
				</item>
				<item>
					<name>健美操，轻</name>
					<calorie1>207</calorie1>
					<calorie2>246</calorie2>
					<calorie3>286</calorie3>
					<calorie4>326</calorie4>
					<id>15</id>
				</item>
				<item>
					<name>巡回培训，最小的休息</name>
					<calorie1>472</calorie1>
					<calorie2>563</calorie2>
					<calorie3>654</calorie3>
					<calorie4>745</calorie4>
					<id>16</id>
				</item>
				<item>
					<name>举重，健美，充满活力</name>
					<calorie1>354</calorie1>
					<calorie2>422</calorie2>
					<calorie3>490</calorie3>
					<calorie4>558</calorie4>
					<id>17</id>
				</item>
				<item>
					<name>举重，轻锻炼</name>
					<calorie1>177</calorie1>
					<calorie2>211</calorie2>
					<calorie3>245</calorie3>
					<calorie4>279</calorie4>
					<id>18</id>
				</item>
				<item>
					<name>健康俱乐部运动</name>
					<calorie1>325</calorie1>
					<calorie2>387</calorie2>
					<calorie3>449</calorie3>
					<calorie4>512</calorie4>
					<id>19</id>
				</item>
				<item>
					<name>楼梯机</name>
					<calorie1>531</calorie1>
					<calorie2>633</calorie2>
					<calorie3>735</calorie3>
					<calorie4>838</calorie4>
					<id>20</id>
				</item>
				<item>
					<name>划船机，光</name>
					<calorie1>207</calorie1>
					<calorie2>246</calorie2>
					<calorie3>286</calorie3>
					<calorie4>326</calorie4>
					<id>21</id>
				</item>
				<item>
					<name>划船机，中度</name>
					<calorie1>413</calorie1>
					<calorie2>493</calorie2>
					<calorie3>572</calorie3>
					<calorie4>651</calorie4>
					<id>22</id>
				</item>
				<item>
					<name>划船机，苍劲</name>
					<calorie1>502</calorie1>
					<calorie2>598</calorie2>
					<calorie3>695</calorie3>
					<calorie4>791</calorie4>
					<id>23</id>
				</item>
				<item>
					<name>划船机，非常剧烈</name>
					<calorie1>708</calorie1>
					<calorie2>844</calorie2>
					<calorie3>981</calorie3>
					<calorie4>1117</calorie4>
					<id>24</id>
				</item>
				<item>
					<name>滑雪机​​</name>
					<calorie1>413</calorie1>
					<calorie2>493</calorie2>
					<calorie3>572</calorie3>
					<calorie4>651</calorie4>
					<id>25</id>
				</item>
				<item>
					<name>健美操，低冲击</name>
					<calorie1>295</calorie1>
					<calorie2>352</calorie2>
					<calorie3>409</calorie3>
					<calorie4>465</calorie4>
					<id>26</id>
				</item>
				<item>
					<name>健美操，高冲击</name>
					<calorie1>413</calorie1>
					<calorie2>493</calorie2>
					<calorie3>572</calorie3>
					<calorie4>651</calorie4>
					<id>27</id>
				</item>
				<item>
					<name>有氧，阶梯有氧</name>
					<calorie1>502</calorie1>
					<calorie2>598</calorie2>
					<calorie3>695</calorie3>
					<calorie4>791</calorie4>
					<id>28</id>
				</item>
				<item>
					<name>健美操，一般</name>
					<calorie1>384</calorie1>
					<calorie2>457</calorie2>
					<calorie3>531</calorie3>
					<calorie4>605</calorie4>
					<id>29</id>
				</item>
				<item>
					<name>Jazzercise</name>
					<calorie1>354</calorie1>
					<calorie2>422</calorie2>
					<calorie3>490</calorie3>
					<calorie4>558</calorie4>
					<id>30</id>
				</item>
				<item>
					<name>哈达瑜伽伸展，</name>
					<calorie1>236</calorie1>
					<calorie2>281</calorie2>
					<calorie3>327</calorie3>
					<calorie4>372</calorie4>
					<id>31</id>
				</item>
				<item>
					<name>轻度拉伸</name>
					<calorie1>148</calorie1>
					<calorie2>176</calorie2>
					<calorie3>204</calorie3>
					<calorie4>233</calorie4>
					<id>32</id>
				</item>
				<item>
					<name>指示有氧健身班</name>
					<calorie1>354</calorie1>
					<calorie2>422</calorie2>
					<calorie3>490</calorie3>
					<calorie4>558</calorie4>
					<id>33</id>
				</item>
				<item>
					<name>水中有氧操</name>
					<calorie1>236</calorie1>
					<calorie2>281</calorie2>
					<calorie3>327</calorie3>
					<calorie4>372</calorie4>
					<id>34</id>
				</item>
				<item>
					<name>芭蕾舞团，扭曲，爵士，自来水</name>
					<calorie1>266</calorie1>
					<calorie2>317</calorie2>
					<calorie3>368</calorie3>
					<calorie4>419</calorie4>
					<id>35</id>
				</item>
				<item>
					<name>交际舞，慢</name>
					<calorie1>177</calorie1>
					<calorie2>211</calorie2>
					<calorie3>245</calorie3>
					<calorie4>279</calorie4>
					<id>36</id>
				</item>
				<item>
					<name>交际舞，快</name>
					<calorie1>325</calorie1>
					<calorie2>387</calorie2>
					<calorie3>449</calorie3>
					<calorie4>512</calorie4>
					<id>37</id>
				</item>
				<item>
					<name>跑步，8kmh（7.5分钟1公里）</name>
					<calorie1>472</calorie1>
					<calorie2>563</calorie2>
					<calorie3>654</calorie3>
					<calorie4>745</calorie4>
					<id>38</id>
				</item>
				<item>
					<name>跑步，8.3kmh（7.22分钟1公里）</name>
					<calorie1>531</calorie1>
					<calorie2>633</calorie2>
					<calorie3>735</calorie3>
					<calorie4>838</calorie4>
					<id>39</id>
				</item>
				<item>
					<name>运行，9.6kmh（6.25分钟1公里）</name>
					<calorie1>590</calorie1>
					<calorie2>704</calorie2>
					<calorie3>817</calorie3>
					<calorie4>931</calorie4>
					<id>40</id>
				</item>
				<item>
					<name>跑步，10.7kmh（5.6分钟1公里）</name>
					<calorie1>649</calorie1>
					<calorie2>774</calorie2>
					<calorie3>899</calorie3>
					<calorie4>1024</calorie4>
					<id>41</id>
				</item>
				<item>
					<name>跑步，11.2kmh（5.3分钟1公里）</name>
					<calorie1>679</calorie1>
					<calorie2>809</calorie2>
					<calorie3>940</calorie3>
					<calorie4>1070</calorie4>
					<id>42</id>
				</item>
				<item>
					<name>跑步，12kmh（5分钟1公里）</name>
					<calorie1>738</calorie1>
					<calorie2>880</calorie2>
					<calorie3>1022</calorie3>
					<calorie4>1163</calorie4>
					<id>43</id>
				</item>
				<item>
					<name>跑步，12.8kmh（4.6分钟1公里）</name>
					<calorie1>797</calorie1>
					<calorie2>950</calorie2>
					<calorie3>1103</calorie3>
					<calorie4>1256</calorie4>
					<id>44</id>
				</item>
				<item>
					<name>跑步，13.8kmh（4.3分1公里）</name>
					<calorie1>826</calorie1>
					<calorie2>985</calorie2>
					<calorie3>1144</calorie3>
					<calorie4>1303</calorie4>
					<id>45</id>
				</item>
				<item>
					<name>跑步，14.4kmh（4.1分钟1公里）</name>
					<calorie1>885</calorie1>
					<calorie2>1056</calorie2>
					<calorie3>1226</calorie3>
					<calorie4>1396</calorie4>
					<id>46</id>
				</item>
				<item>
					<name>跑步，16kmh（3.75分1公里）</name>
					<calorie1>944</calorie1>
					<calorie2>1126</calorie2>
					<calorie3>1308</calorie3>
					<calorie4>1489</calorie4>
					<id>47</id>
				</item>
				<item>
					<name>跑步，17.5kmh（3.4分钟1公里）</name>
					<calorie1>1062</calorie1>
					<calorie2>1267</calorie2>
					<calorie3>1471</calorie3>
					<calorie4>1675</calorie4>
					<id>48</id>
				</item>
				<item>
					<name>跑步，越野</name>
					<calorie1>531</calorie1>
					<calorie2>633</calorie2>
					<calorie3>735</calorie3>
					<calorie4>838</calorie4>
					<id>49</id>
				</item>
				<item>
					<name>跑步，一般</name>
					<calorie1>472</calorie1>
					<calorie2>563</calorie2>
					<calorie3>654</calorie3>
					<calorie4>745</calorie4>
					<id>50</id>
				</item>
				<item>
					<name>在轨道上运行，团队实践</name>
					<calorie1>590</calorie1>
					<calorie2>704</calorie2>
					<calorie3>817</calorie3>
					<calorie4>931</calorie4>
					<id>51</id>
				</item>
				<item>
					<name>跑步，爬楼梯</name>
					<calorie1>885</calorie1>
					<calorie2>1056</calorie2>
					<calorie3>1226</calorie3>
					<calorie4>1396</calorie4>
					<id>52</id>
				</item>
				<item>
					<name>田径（拍摄，铁饼）</name>
					<calorie1>236</calorie1>
					<calorie2>281</calorie2>
					<calorie3>327</calorie3>
					<calorie4>372</calorie4>
					<id>53</id>
				</item>
				<item>
					<name>田径（跳高，撑竿跳高）</name>
					<calorie1>354</calorie1>
					<calorie2>422</calorie2>
					<calorie3>490</calorie3>
					<calorie4>558</calorie4>
					<id>54</id>
				</item>
				<item>
					<name>田径（跨栏）</name>
					<calorie1>590</calorie1>
					<calorie2>704</calorie2>
					<calorie3>817</calorie3>
					<calorie4>931</calorie4>
					<id>55</id>
				</item>
				<item>
					<name>射箭</name>
					<calorie1>207</calorie1>
					<calorie2>246</calorie2>
					<calorie3>286</calorie3>
					<calorie4>326</calorie4>
					<id>56</id>
				</item>
				<item>
					<name>羽毛球</name>
					<calorie1>266</calorie1>
					<calorie2>317</calorie2>
					<calorie3>368</calorie3>
					<calorie4>419</calorie4>
					<id>57</id>
				</item>
				<item>
					<name>篮球比赛，有竞争力的</name>
					<calorie1>472</calorie1>
					<calorie2>563</calorie2>
					<calorie3>654</calorie3>
					<calorie4>745</calorie4>
					<id>58</id>
				</item>
				<item>
					<name>篮球，非游戏</name>
					<calorie1>354</calorie1>
					<calorie2>422</calorie2>
					<calorie3>490</calorie3>
					<calorie4>558</calorie4>
					<id>59</id>
				</item>
				<item>
					<name>篮球，主持</name>
					<calorie1>413</calorie1>
					<calorie2>493</calorie2>
					<calorie3>572</calorie3>
					<calorie4>651</calorie4>
					<id>60</id>
				</item>
				<item>
					<name>篮球，射篮</name>
					<calorie1>266</calorie1>
					<calorie2>317</calorie2>
					<calorie3>368</calorie3>
					<calorie4>419</calorie4>
					<id>61</id>
				</item>
				<item>
					<name>篮球，轮椅</name>
					<calorie1>384</calorie1>
					<calorie2>457</calorie2>
					<calorie3>531</calorie3>
					<calorie4>605</calorie4>
					<id>62</id>
				</item>
				<item>
					<name>跑步，训练，推轮椅</name>
					<calorie1>472</calorie1>
					<calorie2>563</calorie2>
					<calorie3>654</calorie3>
					<calorie4>745</calorie4>
					<id>63</id>
				</item>
				<item>
					<name>台球</name>
					<calorie1>148</calorie1>
					<calorie2>176</calorie2>
					<calorie3>204</calorie3>
					<calorie4>233</calorie4>
					<id>64</id>
				</item>
				<item>
					<name>保龄球</name>
					<calorie1>177</calorie1>
					<calorie2>211</calorie2>
					<calorie3>245</calorie3>
					<calorie4>279</calorie4>
					<id>65</id>
				</item>
				<item>
					<name>拳击，中环</name>
					<calorie1>708</calorie1>
					<calorie2>844</calorie2>
					<calorie3>981</calorie3>
					<calorie4>1117</calorie4>
					<id>66</id>
				</item>
				<item>
					<name>拳击，出气筒</name>
					<calorie1>354</calorie1>
					<calorie2>422</calorie2>
					<calorie3>490</calorie3>
					<calorie4>558</calorie4>
					<id>67</id>
				</item>
				<item>
					<name>拳击陪练</name>
					<calorie1>531</calorie1>
					<calorie2>633</calorie2>
					<calorie3>735</calorie3>
					<calorie4>838</calorie4>
					<id>68</id>
				</item>
				<item>
					<name>教练：足球，篮球，足球</name>
					<calorie1>236</calorie1>
					<calorie2>281</calorie2>
					<calorie3>327</calorie3>
					<calorie4>372</calorie4>
					<id>69</id>
				</item>
				<item>
					<name>板球（击球，投球）</name>
					<calorie1>295</calorie1>
					<calorie2>352</calorie2>
					<calorie3>409</calorie3>
					<calorie4>465</calorie4>
					<id>70</id>
				</item>
				<item>
					<name>槌球</name>
					<calorie1>148</calorie1>
					<calorie2>176</calorie2>
					<calorie3>204</calorie3>
					<calorie4>233</calorie4>
					<id>71</id>
				</item>
				<item>
					<name>冰壶</name>
					<calorie1>236</calorie1>
					<calorie2>281</calorie2>
					<calorie3>327</calorie3>
					<calorie4>372</calorie4>
					<id>72</id>
				</item>
				<item>
					<name>飞镖游戏（墙壁或草坪）</name>
					<calorie1>148</calorie1>
					<calorie2>176</calorie2>
					<calorie3>204</calorie3>
					<calorie4>233</calorie4>
					<id>73</id>
				</item>
				<item>
					<name>击剑</name>
					<calorie1>354</calorie1>
					<calorie2>422</calorie2>
					<calorie3>490</calorie3>
					<calorie4>558</calorie4>
					<id>74</id>
				</item>
				<item>
					<name>足球，有竞争力的</name>
					<calorie1>531</calorie1>
					<calorie2>633</calorie2>
					<calorie3>735</calorie3>
					<calorie4>838</calorie4>
					<id>75</id>
				</item>
				<item>
					<name>足球，触摸，标志，一般</name>
					<calorie1>472</calorie1>
					<calorie2>563</calorie2>
					<calorie3>654</calorie3>
					<calorie4>745</calorie4>
					<id>76</id>
				</item>
				<item>
					<name>足球或棒球，追赶</name>
					<calorie1>148</calorie1>
					<calorie2>176</calorie2>
					<calorie3>204</calorie3>
					<calorie4>233</calorie4>
					<id>77</id>
				</item>
				<item>
					<name>飞盘玩，一般</name>
					<calorie1>177</calorie1>
					<calorie2>211</calorie2>
					<calorie3>245</calorie3>
					<calorie4>279</calorie4>
					<id>78</id>
				</item>
				<item>
					<name>飞盘，飞盘</name>
					<calorie1>472</calorie1>
					<calorie2>563</calorie2>
					<calorie3>654</calorie3>
					<calorie4>745</calorie4>
					<id>79</id>
				</item>
				<item>
					<name>高尔夫球，一般</name>
					<calorie1>266</calorie1>
					<calorie2>317</calorie2>
					<calorie3>368</calorie3>
					<calorie4>419</calorie4>
					<id>80</id>
				</item>
				<item>
					<name>高尔夫球，散步和账面俱乐部</name>
					<calorie1>266</calorie1>
					<calorie2>317</calorie2>
					<calorie3>368</calorie3>
					<calorie4>419</calorie4>
					<id>81</id>
				</item>
				<item>
					<name>高尔夫练习场</name>
					<calorie1>177</calorie1>
					<calorie2>211</calorie2>
					<calorie3>245</calorie3>
					<calorie4>279</calorie4>
					<id>82</id>
				</item>
				<item>
					<name>高尔夫，迷你高尔夫</name>
					<calorie1>177</calorie1>
					<calorie2>211</calorie2>
					<calorie3>245</calorie3>
					<calorie4>279</calorie4>
					<id>83</id>
				</item>
				<item>
					<name>高尔夫球，散步和拉俱乐部</name>
					<calorie1>254</calorie1>
					<calorie2>303</calorie2>
					<calorie3>351</calorie3>
					<calorie4>400</calorie4>
					<id>84</id>
				</item>
				<item>
					<name>高尔夫球，使用电源车</name>
					<calorie1>207</calorie1>
					<calorie2>246</calorie2>
					<calorie3>286</calorie3>
					<calorie4>326</calorie4>
					<id>85</id>
				</item>
				<item>
					<name>体操</name>
					<calorie1>236</calorie1>
					<calorie2>281</calorie2>
					<calorie3>327</calorie3>
					<calorie4>372</calorie4>
					<id>86</id>
				</item>
				<item>
					<name>哈克麻袋</name>
					<calorie1>236</calorie1>
					<calorie2>281</calorie2>
					<calorie3>327</calorie3>
					<calorie4>372</calorie4>
					<id>87</id>
				</item>
				<item>
					<name>手球</name>
					<calorie1>708</calorie1>
					<calorie2>844</calorie2>
					<calorie3>981</calorie3>
					<calorie4>1117</calorie4>
					<id>88</id>
				</item>
				<item>
					<name>手球，团队</name>
					<calorie1>472</calorie1>
					<calorie2>563</calorie2>
					<calorie3>654</calorie3>
					<calorie4>745</calorie4>
					<id>89</id>
				</item>
				<item>
					<name>曲棍球，曲棍球</name>
					<calorie1>472</calorie1>
					<calorie2>563</calorie2>
					<calorie3>654</calorie3>
					<calorie4>745</calorie4>
					<id>90</id>
				</item>
				<item>
					<name>曲棍球，冰球</name>
					<calorie1>472</calorie1>
					<calorie2>563</calorie2>
					<calorie3>654</calorie3>
					<calorie4>745</calorie4>
					<id>91</id>
				</item>
				<item>
					<name>骑一匹马，一般</name>
					<calorie1>236</calorie1>
					<calorie2>281</calorie2>
					<calorie3>327</calorie3>
					<calorie4>372</calorie4>
					<id>92</id>
				</item>
				<item>
					<name>骑马，骑鞍的马</name>
					<calorie1>207</calorie1>
					<calorie2>246</calorie2>
					<calorie3>286</calorie3>
					<calorie4>326</calorie4>
					<id>93</id>
				</item>
				<item>
					<name>骑马，疏导马</name>
					<calorie1>207</calorie1>
					<calorie2>246</calorie2>
					<calorie3>286</calorie3>
					<calorie4>326</calorie4>
					<id>94</id>
				</item>
				<item>
					<name>骑马，小跑</name>
					<calorie1>384</calorie1>
					<calorie2>457</calorie2>
					<calorie3>531</calorie3>
					<calorie4>605</calorie4>
					<id>95</id>
				</item>
				<item>
					<name>骑马，散步</name>
					<calorie1>148</calorie1>
					<calorie2>176</calorie2>
					<calorie3>204</calorie3>
					<calorie4>233</calorie4>
					<id>96</id>
				</item>
				<item>
					<name>赛马，奔腾</name>
					<calorie1>472</calorie1>
					<calorie2>563</calorie2>
					<calorie3>654</calorie3>
					<calorie4>745</calorie4>
					<id>97</id>
				</item>
				<item>
					<name>马疏导，中度</name>
					<calorie1>354</calorie1>
					<calorie2>422</calorie2>
					<calorie3>490</calorie3>
					<calorie4>558</calorie4>
					<id>98</id>
				</item>
				<item>
					<name>马蹄投球</name>
					<calorie1>177</calorie1>
					<calorie2>211</calorie2>
					<calorie3>245</calorie3>
					<calorie4>279</calorie4>
					<id>99</id>
				</item>
				<item>
					<name>回力</name>
					<calorie1>708</calorie1>
					<calorie2>844</calorie2>
					<calorie3>981</calorie3>
					<calorie4>1117</calorie4>
					<id>100</id>
				</item>
				<item>
					<name>武术，柔道，空手道，柔术</name>
					<calorie1>590</calorie1>
					<calorie2>704</calorie2>
					<calorie3>817</calorie3>
					<calorie4>931</calorie4>
					<id>101</id>
				</item>
				<item>
					<name>武术，拳击</name>
					<calorie1>590</calorie1>
					<calorie2>704</calorie2>
					<calorie3>817</calorie3>
					<calorie4>931</calorie4>
					<id>102</id>
				</item>
				<item>
					<name>武术，跆拳道</name>
					<calorie1>590</calorie1>
					<calorie2>704</calorie2>
					<calorie3>817</calorie3>
					<calorie4>931</calorie4>
					<id>103</id>
				</item>
				<item>
					<name>Krav maga培训</name>
					<calorie1>590</calorie1>
					<calorie2>704</calorie2>
					<calorie3>817</calorie3>
					<calorie4>931</calorie4>
					<id>104</id>
				</item>
				<item>
					<name>杂耍</name>
					<calorie1>236</calorie1>
					<calorie2>281</calorie2>
					<calorie3>327</calorie3>
					<calorie4>372</calorie4>
					<id>105</id>
				</item>
				<item>
					<name>蹴鞠</name>
					<calorie1>413</calorie1>
					<calorie2>493</calorie2>
					<calorie3>572</calorie3>
					<calorie4>651</calorie4>
					<id>106</id>
				</item>
				<item>
					<name>长曲棍球</name>
					<calorie1>472</calorie1>
					<calorie2>563</calorie2>
					<calorie3>654</calorie3>
					<calorie4>745</calorie4>
					<id>107</id>
				</item>
				<item>
					<name>定向</name>
					<calorie1>531</calorie1>
					<calorie2>633</calorie2>
					<calorie3>735</calorie3>
					<calorie4>838</calorie4>
					<id>108</id>
				</item>
				<item>
					<name>板球</name>
					<calorie1>354</calorie1>
					<calorie2>422</calorie2>
					<calorie3>490</calorie3>
					<calorie4>558</calorie4>
					<id>109</id>
				</item>
				<item>
					<name>板球，有竞争力的</name>
					<calorie1>590</calorie1>
					<calorie2>704</calorie2>
					<calorie3>817</calorie3>
					<calorie4>931</calorie4>
					<id>110</id>
				</item>
				<item>
					<name>波罗</name>
					<calorie1>472</calorie1>
					<calorie2>563</calorie2>
					<calorie3>654</calorie3>
					<calorie4>745</calorie4>
					<id>111</id>
				</item>
				<item>
					<name>壁球，有竞争力的</name>
					<calorie1>590</calorie1>
					<calorie2>704</calorie2>
					<calorie3>817</calorie3>
					<calorie4>931</calorie4>
					<id>112</id>
				</item>
				<item>
					<name>打壁球</name>
					<calorie1>413</calorie1>
					<calorie2>493</calorie2>
					<calorie3>572</calorie3>
					<calorie4>651</calorie4>
					<id>113</id>
				</item>
				<item>
					<name>攀岩，升摇滚</name>
					<calorie1>649</calorie1>
					<calorie2>774</calorie2>
					<calorie3>899</calorie3>
					<calorie4>1024</calorie4>
					<id>114</id>
				</item>
				<item>
					<name>攀岩，速降</name>
					<calorie1>472</calorie1>
					<calorie2>563</calorie2>
					<calorie3>654</calorie3>
					<calorie4>745</calorie4>
					<id>115</id>
				</item>
				<item>
					<name>跳绳，快</name>
					<calorie1>708</calorie1>
					<calorie2>844</calorie2>
					<calorie3>981</calorie3>
					<calorie4>1117</calorie4>
					<id>116</id>
				</item>
				<item>
					<name>跳绳，中度</name>
					<calorie1>590</calorie1>
					<calorie2>704</calorie2>
					<calorie3>817</calorie3>
					<calorie4>931</calorie4>
					<id>117</id>
				</item>
				<item>
					<name>跳绳，慢</name>
					<calorie1>472</calorie1>
					<calorie2>563</calorie2>
					<calorie3>654</calorie3>
					<calorie4>745</calorie4>
					<id>118</id>
				</item>
				<item>
					<name>橄榄球</name>
					<calorie1>590</calorie1>
					<calorie2>704</calorie2>
					<calorie3>817</calorie3>
					<calorie4>931</calorie4>
					<id>119</id>
				</item>
				<item>
					<name>沙狐球，草地保龄球</name>
					<calorie1>177</calorie1>
					<calorie2>211</calorie2>
					<calorie3>245</calorie3>
					<calorie4>279</calorie4>
					<id>120</id>
				</item>
				<item>
					<name>滑板</name>
					<calorie1>295</calorie1>
					<calorie2>352</calorie2>
					<calorie3>409</calorie3>
					<calorie4>465</calorie4>
					<id>121</id>
				</item>
				<item>
					<name>轮滑</name>
					<calorie1>413</calorie1>
					<calorie2>493</calorie2>
					<calorie3>572</calorie3>
					<calorie4>651</calorie4>
					<id>122</id>
				</item>
				<item>
					<name>轮滑，单排旱冰</name>
					<calorie1>708</calorie1>
					<calorie2>844</calorie2>
					<calorie3>981</calorie3>
					<calorie4>1117</calorie4>
					<id>123</id>
				</item>
				<item>
					<name>跳伞</name>
					<calorie1>177</calorie1>
					<calorie2>211</calorie2>
					<calorie3>245</calorie3>
					<calorie4>279</calorie4>
					<id>124</id>
				</item>
				<item>
					<name>足球，有竞争力的</name>
					<calorie1>590</calorie1>
					<calorie2>704</calorie2>
					<calorie3>817</calorie3>
					<calorie4>931</calorie4>
					<id>125</id>
				</item>
				<item>
					<name>踢足球</name>
					<calorie1>413</calorie1>
					<calorie2>493</calorie2>
					<calorie3>572</calorie3>
					<calorie4>651</calorie4>
					<id>126</id>
				</item>
				<item>
					<name>垒球或棒球</name>
					<calorie1>295</calorie1>
					<calorie2>352</calorie2>
					<calorie3>409</calorie3>
					<calorie4>465</calorie4>
					<id>127</id>
				</item>
				<item>
					<name>垒球，主持</name>
					<calorie1>236</calorie1>
					<calorie2>281</calorie2>
					<calorie3>327</calorie3>
					<calorie4>372</calorie4>
					<id>128</id>
				</item>
				<item>
					<name>垒球，投球</name>
					<calorie1>354</calorie1>
					<calorie2>422</calorie2>
					<calorie3>490</calorie3>
					<calorie4>558</calorie4>
					<id>129</id>
				</item>
				<item>
					<name>壁球</name>
					<calorie1>708</calorie1>
					<calorie2>844</calorie2>
					<calorie3>981</calorie3>
					<calorie4>1117</calorie4>
					<id>130</id>
				</item>
				<item>
					<name>乒乓球</name>
					<calorie1>236</calorie1>
					<calorie2>281</calorie2>
					<calorie3>327</calorie3>
					<calorie4>372</calorie4>
					<id>131</id>
				</item>
				<item>
					<name>太极拳</name>
					<calorie1>236</calorie1>
					<calorie2>281</calorie2>
					<calorie3>327</calorie3>
					<calorie4>372</calorie4>
					<id>132</id>
				</item>
				<item>
					<name>网球</name>
					<calorie1>413</calorie1>
					<calorie2>493</calorie2>
					<calorie3>572</calorie3>
					<calorie4>651</calorie4>
					<id>133</id>
				</item>
				<item>
					<name>网球，双打</name>
					<calorie1>354</calorie1>
					<calorie2>422</calorie2>
					<calorie3>490</calorie3>
					<calorie4>558</calorie4>
					<id>134</id>
				</item>
				<item>
					<name>网球，单身</name>
					<calorie1>472</calorie1>
					<calorie2>563</calorie2>
					<calorie3>654</calorie3>
					<calorie4>745</calorie4>
					<id>135</id>
				</item>
				<item>
					<name>蹦床</name>
					<calorie1>207</calorie1>
					<calorie2>246</calorie2>
					<calorie3>286</calorie3>
					<calorie4>326</calorie4>
					<id>136</id>
				</item>
				<item>
					<name>排球，竞争</name>
					<calorie1>472</calorie1>
					<calorie2>563</calorie2>
					<calorie3>654</calorie3>
					<calorie4>745</calorie4>
					<id>137</id>
				</item>
				<item>
					<name>排球</name>
					<calorie1>177</calorie1>
					<calorie2>211</calorie2>
					<calorie3>245</calorie3>
					<calorie4>279</calorie4>
					<id>138</id>
				</item>
				<item>
					<name>排球，沙滩</name>
					<calorie1>472</calorie1>
					<calorie2>563</calorie2>
					<calorie3>654</calorie3>
					<calorie4>745</calorie4>
					<id>139</id>
				</item>
				<item>
					<name>摔角</name>
					<calorie1>354</calorie1>
					<calorie2>422</calorie2>
					<calorie3>490</calorie3>
					<calorie4>558</calorie4>
					<id>140</id>
				</item>
				<item>
					<name>Wallyball</name>
					<calorie1>413</calorie1>
					<calorie2>493</calorie2>
					<calorie3>572</calorie3>
					<calorie4>651</calorie4>
					<id>141</id>
				</item>
				<item>
					<name>背包旅行，远足包</name>
					<calorie1>413</calorie1>
					<calorie2>493</calorie2>
					<calorie3>572</calorie3>
					<calorie4>651</calorie4>
					<id>142</id>
				</item>
				<item>
					<name>携带婴儿的水平地面</name>
					<calorie1>207</calorie1>
					<calorie2>246</calorie2>
					<calorie3>286</calorie3>
					<calorie4>326</calorie4>
					<id>143</id>
				</item>
				<item>
					<name>背婴儿，楼上</name>
					<calorie1>295</calorie1>
					<calorie2>352</calorie2>
					<calorie3>409</calorie3>
					<calorie4>465</calorie4>
					<id>144</id>
				</item>
				<item>
					<name>背东西，7.2到10.8公斤，楼上</name>
					<calorie1>354</calorie1>
					<calorie2>422</calorie2>
					<calorie3>490</calorie3>
					<calorie4>558</calorie4>
					<id>145</id>
				</item>
				<item>
					<name>背东西，10.9至22.2公斤，楼上</name>
					<calorie1>472</calorie1>
					<calorie2>563</calorie2>
					<calorie3>654</calorie3>
					<calorie4>745</calorie4>
					<id>146</id>
				</item>
				<item>
					<name>站立，跟孩子一起玩，光</name>
					<calorie1>165</calorie1>
					<calorie2>197</calorie2>
					<calorie3>229</calorie3>
					<calorie4>261</calorie4>
					<id>147</id>
				</item>
				<item>
					<name>走/跑，玩儿童，中度</name>
					<calorie1>236</calorie1>
					<calorie2>281</calorie2>
					<calorie3>327</calorie3>
					<calorie4>372</calorie4>
					<id>148</id>
				</item>
				<item>
					<name>走/跑，玩儿童，苍劲</name>
					<calorie1>295</calorie1>
					<calorie2>352</calorie2>
					<calorie3>409</calorie3>
					<calorie4>465</calorie4>
					<id>149</id>
				</item>
				<item>
					<name>背小儿童</name>
					<calorie1>177</calorie1>
					<calorie2>211</calorie2>
					<calorie3>245</calorie3>
					<calorie4>279</calorie4>
					<id>150</id>
				</item>
				<item>
					<name>装货，卸货车</name>
					<calorie1>177</calorie1>
					<calorie2>211</calorie2>
					<calorie3>245</calorie3>
					<calorie4>279</calorie4>
					<id>151</id>
				</item>
				<item>
					<name>爬山，携带多达4公斤</name>
					<calorie1>413</calorie1>
					<calorie2>493</calorie2>
					<calorie3>572</calorie3>
					<calorie4>651</calorie4>
					<id>152</id>
				</item>
				<item>
					<name>爬山，携带4.1到9.0公斤东西</name>
					<calorie1>443</calorie1>
					<calorie2>528</calorie2>
					<calorie3>613</calorie3>
					<calorie4>698</calorie4>
					<id>153</id>
				</item>
				<item>
					<name>爬山，携带9.1〜19.0公斤东西</name>
					<calorie1>472</calorie1>
					<calorie2>563</calorie2>
					<calorie3>654</calorie3>
					<calorie4>745</calorie4>
					<id>154</id>
				</item>
				<item>
					<name>爬山，携带超过19.1公斤东西</name>
					<calorie1>531</calorie1>
					<calorie2>633</calorie2>
					<calorie3>735</calorie3>
					<calorie4>838</calorie4>
					<id>155</id>
				</item>
				<item>
					<name>走下楼</name>
					<calorie1>177</calorie1>
					<calorie2>211</calorie2>
					<calorie3>245</calorie3>
					<calorie4>279</calorie4>
					<id>156</id>
				</item>
				<item>
					<name>徒步旅行，越野</name>
					<calorie1>354</calorie1>
					<calorie2>422</calorie2>
					<calorie3>490</calorie3>
					<calorie4>558</calorie4>
					<id>157</id>
				</item>
				<item>
					<name>观鸟</name>
					<calorie1>148</calorie1>
					<calorie2>176</calorie2>
					<calorie3>204</calorie3>
					<calorie4>233</calorie4>
					<id>158</id>
				</item>
				<item>
					<name>步操，迅速，军事</name>
					<calorie1>384</calorie1>
					<calorie2>457</calorie2>
					<calorie3>531</calorie3>
					<calorie4>605</calorie4>
					<id>159</id>
				</item>
				<item>
					<name>儿童的游戏，跳房子，躲避球</name>
					<calorie1>295</calorie1>
					<calorie2>352</calorie2>
					<calorie3>409</calorie3>
					<calorie4>465</calorie4>
					<id>160</id>
				</item>
				<item>
					<name>推婴儿车或步行儿童</name>
					<calorie1>148</calorie1>
					<calorie2>176</calorie2>
					<calorie3>204</calorie3>
					<calorie4>233</calorie4>
					<id>161</id>
				</item>
				<item>
					<name>推着轮椅</name>
					<calorie1>236</calorie1>
					<calorie2>281</calorie2>
					<calorie3>327</calorie3>
					<calorie4>372</calorie4>
					<id>162</id>
				</item>
				<item>
					<name>竞走</name>
					<calorie1>384</calorie1>
					<calorie2>457</calorie2>
					<calorie3>531</calorie3>
					<calorie4>605</calorie4>
					<id>163</id>
				</item>
				<item>
					<name>攀岩，登山</name>
					<calorie1>472</calorie1>
					<calorie2>563</calorie2>
					<calorie3>654</calorie3>
					<calorie4>745</calorie4>
					<id>164</id>
				</item>
				<item>
					<name>走使用拐杖</name>
					<calorie1>295</calorie1>
					<calorie2>352</calorie2>
					<calorie3>409</calorie3>
					<calorie4>465</calorie4>
					<id>165</id>
				</item>
				<item>
					<name>遛狗</name>
					<calorie1>177</calorie1>
					<calorie2>211</calorie2>
					<calorie3>245</calorie3>
					<calorie4>279</calorie4>
					<id>166</id>
				</item>
				<item>
					<name>步行／走，3.2kmh，速度很慢</name>
					<calorie1>118</calorie1>
					<calorie2>141</calorie2>
					<calorie3>163</calorie3>
					<calorie4>186</calorie4>
					<id>167</id>
				</item>
				<item>
					<name>步行／走，3.2kmh</name>
					<calorie1>148</calorie1>
					<calorie2>176</calorie2>
					<calorie3>204</calorie3>
					<calorie4>233</calorie4>
					<id>168</id>
				</item>
				<item>
					<name>步行／走，4.0kmh</name>
					<calorie1>177</calorie1>
					<calorie2>211</calorie2>
					<calorie3>245</calorie3>
					<calorie4>279</calorie4>
					<id>169</id>
				</item>
				<item>
					<name>步行／走，4.8kmh，中度</name>
					<calorie1>195</calorie1>
					<calorie2>232</calorie2>
					<calorie3>270</calorie3>
					<calorie4>307</calorie4>
					<id>170</id>
				</item>
				<item>
					<name>步行／走，5.6kmh，轻快的步伐</name>
					<calorie1>224</calorie1>
					<calorie2>267</calorie2>
					<calorie3>311</calorie3>
					<calorie4>354</calorie4>
					<id>171</id>
				</item>
				<item>
					<name>步行／走，5.6kmh，上坡</name>
					<calorie1>354</calorie1>
					<calorie2>422</calorie2>
					<calorie3>490</calorie3>
					<calorie4>558</calorie4>
					<id>172</id>
				</item>
				<item>
					<name>步行／走，6.4kmh，十分亮眼</name>
					<calorie1>295</calorie1>
					<calorie2>352</calorie2>
					<calorie3>409</calorie3>
					<calorie4>465</calorie4>
					<id>173</id>
				</item>
				<item>
					<name>步行／走，7.2kmh</name>
					<calorie1>372</calorie1>
					<calorie2>443</calorie2>
					<calorie3>515</calorie3>
					<calorie4>586</calorie4>
					<id>174</id>
				</item>
				<item>
					<name>步行／走，8.0kmh</name>
					<calorie1>472</calorie1>
					<calorie2>563</calorie2>
					<calorie3>654</calorie3>
					<calorie4>745</calorie4>
					<id>175</id>
				</item>
				<item>
					<name>划船，电力，快艇</name>
					<calorie1>148</calorie1>
					<calorie2>176</calorie2>
					<calorie3>204</calorie3>
					<calorie4>233</calorie4>
					<id>176</id>
				</item>
				<item>
					<name>划独木舟，野营</name>
					<calorie1>236</calorie1>
					<calorie2>281</calorie2>
					<calorie3>327</calorie3>
					<calorie4>372</calorie4>
					<id>177</id>
				</item>
				<item>
					<name>划独木舟，划船，轻</name>
					<calorie1>177</calorie1>
					<calorie2>211</calorie2>
					<calorie3>245</calorie3>
					<calorie4>279</calorie4>
					<id>178</id>
				</item>
				<item>
					<name>划独木舟，划船，中度</name>
					<calorie1>413</calorie1>
					<calorie2>493</calorie2>
					<calorie3>572</calorie3>
					<calorie4>651</calorie4>
					<id>179</id>
				</item>
				<item>
					<name>划独木舟，划船，剧烈</name>
					<calorie1>708</calorie1>
					<calorie2>844</calorie2>
					<calorie3>981</calorie3>
					<calorie4>1117</calorie4>
					<id>180</id>
				</item>
				<item>
					<name>船员，艇，赛艇，竞争</name>
					<calorie1>708</calorie1>
					<calorie2>844</calorie2>
					<calorie3>981</calorie3>
					<calorie4>1117</calorie4>
					<id>181</id>
				</item>
				<item>
					<name>皮划艇</name>
					<calorie1>295</calorie1>
					<calorie2>352</calorie2>
					<calorie3>409</calorie3>
					<calorie4>465</calorie4>
					<id>182</id>
				</item>
				<item>
					<name>桨船</name>
					<calorie1>236</calorie1>
					<calorie2>281</calorie2>
					<calorie3>327</calorie3>
					<calorie4>372</calorie4>
					<id>183</id>
				</item>
				<item>
					<name>帆板，帆船</name>
					<calorie1>177</calorie1>
					<calorie2>211</calorie2>
					<calorie3>245</calorie3>
					<calorie4>279</calorie4>
					<id>184</id>
				</item>
				<item>
					<name>帆船，竞争</name>
					<calorie1>295</calorie1>
					<calorie2>352</calorie2>
					<calorie3>409</calorie3>
					<calorie4>465</calorie4>
					<id>185</id>
				</item>
				<item>
					<name>帆船，游艇，海洋帆船</name>
					<calorie1>177</calorie1>
					<calorie2>211</calorie2>
					<calorie3>245</calorie3>
					<calorie4>279</calorie4>
					<id>186</id>
				</item>
				<item>
					<name>滑雪，滑水</name>
					<calorie1>354</calorie1>
					<calorie2>422</calorie2>
					<calorie3>490</calorie3>
					<calorie4>558</calorie4>
					<id>187</id>
				</item>
				<item>
					<name>滑雪</name>
					<calorie1>413</calorie1>
					<calorie2>493</calorie2>
					<calorie3>572</calorie3>
					<calorie4>651</calorie4>
					<id>188</id>
				</item>
				<item>
					<name>皮肤潜水，快速</name>
					<calorie1>944</calorie1>
					<calorie2>1126</calorie2>
					<calorie3>1308</calorie3>
					<calorie4>1489</calorie4>
					<id>189</id>
				</item>
				<item>
					<name>皮肤潜水，中度</name>
					<calorie1>738</calorie1>
					<calorie2>880</calorie2>
					<calorie3>1022</calorie3>
					<calorie4>1163</calorie4>
					<id>190</id>
				</item>
				<item>
					<name>皮肤潜水，潜水</name>
					<calorie1>413</calorie1>
					<calorie2>493</calorie2>
					<calorie3>572</calorie3>
					<calorie4>651</calorie4>
					<id>191</id>
				</item>
				<item>
					<name>浮潜</name>
					<calorie1>295</calorie1>
					<calorie2>352</calorie2>
					<calorie3>409</calorie3>
					<calorie4>465</calorie4>
					<id>192</id>
				</item>
				<item>
					<name>冲浪，冲浪或板冲浪</name>
					<calorie1>177</calorie1>
					<calorie2>211</calorie2>
					<calorie3>245</calorie3>
					<calorie4>279</calorie4>
					<id>193</id>
				</item>
				<item>
					<name>白水漂流，皮划艇，独木舟</name>
					<calorie1>295</calorie1>
					<calorie2>352</calorie2>
					<calorie3>409</calorie3>
					<calorie4>465</calorie4>
					<id>194</id>
				</item>
				<item>
					<name>游泳，自由泳，快</name>
					<calorie1>590</calorie1>
					<calorie2>704</calorie2>
					<calorie3>817</calorie3>
					<calorie4>931</calorie4>
					<id>195</id>
				</item>
				<item>
					<name>游泳，自由泳，慢</name>
					<calorie1>413</calorie1>
					<calorie2>493</calorie2>
					<calorie3>572</calorie3>
					<calorie4>651</calorie4>
					<id>196</id>
				</item>
				<item>
					<name>游泳仰泳</name>
					<calorie1>413</calorie1>
					<calorie2>493</calorie2>
					<calorie3>572</calorie3>
					<calorie4>651</calorie4>
					<id>197</id>
				</item>
				<item>
					<name>游泳蛙泳</name>
					<calorie1>590</calorie1>
					<calorie2>704</calorie2>
					<calorie3>817</calorie3>
					<calorie4>931</calorie4>
					<id>198</id>
				</item>
				<item>
					<name>游泳蝴蝶</name>
					<calorie1>649</calorie1>
					<calorie2>774</calorie2>
					<calorie3>899</calorie3>
					<calorie4>1024</calorie4>
					<id>199</id>
				</item>
				<item>
					<name>悠闲地游泳，而不是圈</name>
					<calorie1>354</calorie1>
					<calorie2>422</calorie2>
					<calorie3>490</calorie3>
					<calorie4>558</calorie4>
					<id>200</id>
				</item>
				<item>
					<name>游泳侧泳</name>
					<calorie1>472</calorie1>
					<calorie2>563</calorie2>
					<calorie3>654</calorie3>
					<calorie4>745</calorie4>
					<id>201</id>
				</item>
				<item>
					<name>游泳同步</name>
					<calorie1>472</calorie1>
					<calorie2>563</calorie2>
					<calorie3>654</calorie3>
					<calorie4>745</calorie4>
					<id>202</id>
				</item>
				<item>
					<name>游泳，踩水，快速，剧烈</name>
					<calorie1>590</calorie1>
					<calorie2>704</calorie2>
					<calorie3>817</calorie3>
					<calorie4>931</calorie4>
					<id>203</id>
				</item>
				<item>
					<name>游泳，踩水，中度</name>
					<calorie1>236</calorie1>
					<calorie2>281</calorie2>
					<calorie3>327</calorie3>
					<calorie4>372</calorie4>
					<id>204</id>
				</item>
				<item>
					<name>水中有氧操，水中​​健美操</name>
					<calorie1>236</calorie1>
					<calorie2>281</calorie2>
					<calorie3>327</calorie3>
					<calorie4>372</calorie4>
					<id>205</id>
				</item>
				<item>
					<name>水球</name>
					<calorie1>590</calorie1>
					<calorie2>704</calorie2>
					<calorie3>817</calorie3>
					<calorie4>931</calorie4>
					<id>206</id>
				</item>
				<item>
					<name>水上排球</name>
					<calorie1>177</calorie1>
					<calorie2>211</calorie2>
					<calorie3>245</calorie3>
					<calorie4>279</calorie4>
					<id>207</id>
				</item>
				<item>
					<name>水中慢跑</name>
					<calorie1>472</calorie1>
					<calorie2>563</calorie2>
					<calorie3>654</calorie3>
					<calorie4>745</calorie4>
					<id>208</id>
				</item>
				<item>
					<name>跳水，跳板或平台</name>
					<calorie1>177</calorie1>
					<calorie2>211</calorie2>
					<calorie3>245</calorie3>
					<calorie4>279</calorie4>
					<id>209</id>
				</item>
				<item>
					<name>溜冰，小于14.48kmh</name>
					<calorie1>325</calorie1>
					<calorie2>387</calorie2>
					<calorie3>449</calorie3>
					<calorie4>512</calorie4>
					<id>210</id>
				</item>
				<item>
					<name>溜冰，平均车速</name>
					<calorie1>413</calorie1>
					<calorie2>493</calorie2>
					<calorie3>572</calorie3>
					<calorie4>651</calorie4>
					<id>211</id>
				</item>
				<item>
					<name>溜冰，快速</name>
					<calorie1>531</calorie1>
					<calorie2>633</calorie2>
					<calorie3>735</calorie3>
					<calorie4>838</calorie4>
					<id>212</id>
				</item>
				<item>
					<name>速度滑冰，冰，有竞争力的</name>
					<calorie1>885</calorie1>
					<calorie2>1056</calorie2>
					<calorie3>1226</calorie3>
					<calorie4>1396</calorie4>
					<id>213</id>
				</item>
				<item>
					<name>越野滑雪，速度慢</name>
					<calorie1>413</calorie1>
					<calorie2>493</calorie2>
					<calorie3>572</calorie3>
					<calorie4>651</calorie4>
					<id>214</id>
				</item>
				<item>
					<name>越野滑雪，中度</name>
					<calorie1>472</calorie1>
					<calorie2>563</calorie2>
					<calorie3>654</calorie3>
					<calorie4>745</calorie4>
					<id>215</id>
				</item>
				<item>
					<name>越野滑雪，苍劲</name>
					<calorie1>531</calorie1>
					<calorie2>633</calorie2>
					<calorie3>735</calorie3>
					<calorie4>838</calorie4>
					<id>216</id>
				</item>
				<item>
					<name>越野滑雪，赛车</name>
					<calorie1>826</calorie1>
					<calorie2>985</calorie2>
					<calorie3>1144</calorie3>
					<calorie4>1303</calorie4>
					<id>217</id>
				</item>
				<item>
					<name>越野滑雪，上坡</name>
					<calorie1>974</calorie1>
					<calorie2>1161</calorie2>
					<calorie3>1348</calorie3>
					<calorie4>1536</calorie4>
					<id>218</id>
				</item>
				<item>
					<name>滑雪，高山滑雪，光</name>
					<calorie1>295</calorie1>
					<calorie2>352</calorie2>
					<calorie3>409</calorie3>
					<calorie4>465</calorie4>
					<id>219</id>
				</item>
				<item>
					<name>速降滑雪，中度</name>
					<calorie1>354</calorie1>
					<calorie2>422</calorie2>
					<calorie3>490</calorie3>
					<calorie4>558</calorie4>
					<id>220</id>
				</item>
				<item>
					<name>速降滑雪，赛车</name>
					<calorie1>472</calorie1>
					<calorie2>563</calorie2>
					<calorie3>654</calorie3>
					<calorie4>745</calorie4>
					<id>221</id>
				</item>
				<item>
					<name>的雪橇，tobagganing，雪橇</name>
					<calorie1>413</calorie1>
					<calorie2>493</calorie2>
					<calorie3>572</calorie3>
					<calorie4>651</calorie4>
					<id>222</id>
				</item>
				<item>
					<name>雪鞋</name>
					<calorie1>472</calorie1>
					<calorie2>563</calorie2>
					<calorie3>654</calorie3>
					<calorie4>745</calorie4>
					<id>223</id>
				</item>
				<item>
					<name>雪地摩托车</name>
					<calorie1>207</calorie1>
					<calorie2>246</calorie2>
					<calorie3>286</calorie3>
					<calorie4>326</calorie4>
					<id>224</id>
				</item>
				<item>
					<name>一般家务</name>
					<calorie1>207</calorie1>
					<calorie2>246</calorie2>
					<calorie3>286</calorie3>
					<calorie4>326</calorie4>
					<id>225</id>
				</item>
				<item>
					<name>清洗水槽</name>
					<calorie1>295</calorie1>
					<calorie2>352</calorie2>
					<calorie3>409</calorie3>
					<calorie4>465</calorie4>
					<id>226</id>
				</item>
				<item>
					<name>绘画</name>
					<calorie1>266</calorie1>
					<calorie2>317</calorie2>
					<calorie3>368</calorie3>
					<calorie4>419</calorie4>
					<id>227</id>
				</item>
				<item>
					<name>坐，打动物</name>
					<calorie1>148</calorie1>
					<calorie2>176</calorie2>
					<calorie3>204</calorie3>
					<calorie4>233</calorie4>
					<id>228</id>
				</item>
				<item>
					<name>走/跑，玩动物</name>
					<calorie1>236</calorie1>
					<calorie2>281</calorie2>
					<calorie3>327</calorie3>
					<calorie4>372</calorie4>
					<id>229</id>
				</item>
				<item>
					<name>沐浴狗</name>
					<calorie1>207</calorie1>
					<calorie2>246</calorie2>
					<calorie3>286</calorie3>
					<calorie4>326</calorie4>
					<id>230</id>
				</item>
				<item>
					<name>割草机修剪草坪，散步，电力</name>
					<calorie1>325</calorie1>
					<calorie2>387</calorie2>
					<calorie3>449</calorie3>
					<calorie4>512</calorie4>
					<id>231</id>
				</item>
				<item>
					<name>割草，割草机</name>
					<calorie1>148</calorie1>
					<calorie2>176</calorie2>
					<calorie3>204</calorie3>
					<calorie4>233</calorie4>
					<id>232</id>
				</item>
				<item>
					<name>散步，吹雪机</name>
					<calorie1>207</calorie1>
					<calorie2>246</calorie2>
					<calorie3>286</calorie3>
					<calorie4>326</calorie4>
					<id>233</id>
				</item>
				<item>
					<name>骑马，吹雪机</name>
					<calorie1>177</calorie1>
					<calorie2>211</calorie2>
					<calorie3>245</calorie3>
					<calorie4>279</calorie4>
					<id>234</id>
				</item>
				<item>
					<name>铲雪的手</name>
					<calorie1>354</calorie1>
					<calorie2>422</calorie2>
					<calorie3>490</calorie3>
					<calorie4>558</calorie4>
					<id>235</id>
				</item>
				<item>
					<name>耙草坪</name>
					<calorie1>254</calorie1>
					<calorie2>303</calorie2>
					<calorie3>351</calorie3>
					<calorie4>400</calorie4>
					<id>236</id>
				</item>
				<item>
					<name>园艺，一般</name>
					<calorie1>236</calorie1>
					<calorie2>281</calorie2>
					<calorie3>327</calorie3>
					<calorie4>372</calorie4>
					<id>237</id>
				</item>
				<item>
					<name>套袋草，树叶</name>
					<calorie1>236</calorie1>
					<calorie2>281</calorie2>
					<calorie3>327</calorie3>
					<calorie4>372</calorie4>
					<id>238</id>
				</item>
				<item>
					<name>浇水的草坪或花园</name>
					<calorie1>89</calorie1>
					<calorie2>106</calorie2>
					<calorie3>123</calorie3>
					<calorie4>140</calorie4>
					<id>239</id>
				</item>
				<item>
					<name>除草，培育花园</name>
					<calorie1>266</calorie1>
					<calorie2>317</calorie2>
					<calorie3>368</calorie3>
					<calorie4>419</calorie4>
					<id>240</id>
				</item>
				<item>
					<name>木工，一般</name>
					<calorie1>207</calorie1>
					<calorie2>246</calorie2>
					<calorie3>286</calorie3>
					<calorie4>326</calorie4>
					<id>241</id>
				</item>
				<item>
					<name>搬运重物</name>
					<calorie1>472</calorie1>
					<calorie2>563</calorie2>
					<calorie3>654</calorie3>
					<calorie4>745</calorie4>
					<id>242</id>
				</item>
				<item>
					<name>账面楼上的中等载荷</name>
					<calorie1>472</calorie1>
					<calorie2>563</calorie2>
					<calorie3>654</calorie3>
					<calorie4>745</calorie4>
					<id>243</id>
				</item>
				<item>
					<name>一般清洗</name>
					<calorie1>207</calorie1>
					<calorie2>246</calorie2>
					<calorie3>286</calorie3>
					<calorie4>326</calorie4>
					<id>244</id>
				</item>
				<item>
					<name>清洁，除尘</name>
					<calorie1>148</calorie1>
					<calorie2>176</calorie2>
					<calorie3>204</calorie3>
					<calorie4>233</calorie4>
					<id>245</id>
				</item>
				<item>
					<name>取出垃圾桶</name>
					<calorie1>177</calorie1>
					<calorie2>211</calorie2>
					<calorie3>245</calorie3>
					<calorie4>279</calorie4>
					<id>246</id>
				</item>
				<item>
					<name>散步，推着轮椅</name>
					<calorie1>236</calorie1>
					<calorie2>281</calorie2>
					<calorie3>327</calorie3>
					<calorie4>372</calorie4>
					<id>247</id>
				</item>
				<item>
					<name>教体育，运动类</name>
					<calorie1>236</calorie1>
					<calorie2>281</calorie2>
					<calorie3>327</calorie3>
					<calorie4>372</calorie4>
					<id>248</id>
				</item>
				<item>
					<name>教运动类</name>
					<calorie1>384</calorie1>
					<calorie2>457</calorie2>
					<calorie3>531</calorie3>
					<calorie4>605</calorie4>
					<id>249</id>
				</item>

			</items>
</page>
